README.txt
setup.cfg
setup.py
mio/__init__.py
mio/reader/__init__.py
mio/reader/jtm/__init__.py
mio/reader/jtm/_json.py
mio/reader/jtm/consts.py
mio/reader/jtm/lexer.py
mio/reader/jtm/parser.py
tm.reader.jtm.egg-info/PKG-INFO
tm.reader.jtm.egg-info/SOURCES.txt
tm.reader.jtm.egg-info/dependency_links.txt
tm.reader.jtm.egg-info/entry_points.txt
tm.reader.jtm.egg-info/namespace_packages.txt
tm.reader.jtm.egg-info/not-zip-safe
tm.reader.jtm.egg-info/requires.txt
tm.reader.jtm.egg-info/top_level.txt